ayw/__init__.py
ayw/ayw.py
ayw/resources/quotes.txt
ayw-0.0.6.dist-info/LICENSE
ayw-0.0.6.dist-info/METADATA
ayw-0.0.6.dist-info/WHEEL
ayw-0.0.6.dist-info/top_level.txt
ayw-0.0.6.dist-info/RECORD
